oarc_log/__init__.py
oarc_log/log.py
oarc_log-0.1.1.dist-info/licenses/LICENSE
tests/log_test.py
oarc_log-0.1.1.dist-info/METADATA
oarc_log-0.1.1.dist-info/WHEEL
oarc_log-0.1.1.dist-info/top_level.txt
oarc_log-0.1.1.dist-info/RECORD
