Metadata-Version: 2.4
Name: oarc-log
Version: 0.1.1
Summary: A simple Context-Aware Logger for Python with debug logging for Ollama Agent Roll Cage (OARC).
Author: OARC Team
License-Expression: Apache-2.0
Project-URL: Homepage, https://github.com/Ollama-Agent-Roll-Cage/oarc-log
Project-URL: Bug Tracker, https://github.com/Ollama-Agent-Roll-Cage/oarc-log/issues
Classifier: Development Status :: 4 - Beta
Classifier: Intended Audience :: Developers
Classifier: Programming Language :: Python :: 3
Classifier: Programming Language :: Python :: 3.10
Classifier: Programming Language :: Python :: 3.11
Classifier: Programming Language :: Python :: 3.12
Classifier: Programming Language :: Python :: 3.13
Classifier: Programming Language :: Python :: 3.14
Requires-Python: >=3.10
License-File: LICENSE
Provides-Extra: dev
Requires-Dist: black; extra == "dev"
Requires-Dist: isort; extra == "dev"
Requires-Dist: mypy; extra == "dev"
Requires-Dist: pytest; extra == "dev"
Requires-Dist: pytest-cov; extra == "dev"
Requires-Dist: pytest-asyncio; extra == "dev"
Requires-Dist: flake8; extra == "dev"
Requires-Dist: pydocstyle; extra == "dev"
Dynamic: license-file
